LICENSE
MANIFEST.in
setup.py
bin/ut2il.py
uTorrent/__init__.py
uTorrent/constants.py
uTorrent/uTorrent.py
uTorrent.Py.egg-info/PKG-INFO
uTorrent.Py.egg-info/SOURCES.txt
uTorrent.Py.egg-info/dependency_links.txt
uTorrent.Py.egg-info/top_level.txt