Metadata-Version: 1.0
Name: uTorrent.Py
Version: 0.1.1
Summary: Mobile Notifications for Transmission Downloads
Home-page: http://github.com/micahr/uTorrent.Py/
Author: Rob Crowther
Author-email: weilawei@gmail.com
License: GNU LGPL
Platform: UNKNOWN
Classifier: Development Status :: 3 - Alpha
Classifier: License :: OSI Approved :: GNU Library or Lesser General Public License (LGPL)
Classifier: Programming Language :: Python
Classifier: Programming Language :: Python :: 2.5
Classifier: Programming Language :: Python :: 2.6
